azlog/__init__.py
azlog-0.1.1.dist-info/WHEEL
azlog-0.1.1.dist-info/METADATA
azlog-0.1.1.dist-info/RECORD
