Metadata-Version: 2.1
Name: azlog
Version: 0.1.1
Summary: Python module to ease Azure DevOps pipelines logging commands
License: MIT
Author-email: Jonathan Scherrer <jonathan.s.scherrer@gmail.com>
Requires-Python: >=3.7
